[
    {
        "className": "G2",
        "axes": [
            {
                "axis": "Mid",
                "value": 21.81
            },
            {
                "axis": "ADC",
                "value": 23.46
            },
            {
                "axis": "Support",
                "value": 14.65
            },
            {
                "axis": "Jungle",
                "value": 19.97
            },
            {
                "axis": "Top",
                "value": 20.11
            }
        ]
    },
    {
        "className": "FNC",
        "axes": [
            {
                "axis": "Mid",
                "value": 22.37
            },
            {
                "axis": "ADC",
                "value": 23.9
            },
            {
                "axis": "Support",
                "value": 14.58
            },
            {
                "axis": "Jungle",
                "value": 19.47
            },
            {
                "axis": "Top",
                "value": 19.67
            }
        ]
    },
    {
        "className": "OG",
        "axes": [
            {
                "axis": "Mid",
                "value": 22.6
            },
            {
                "axis": "ADC",
                "value": 22.91
            },
            {
                "axis": "Support",
                "value": 14.73
            },
            {
                "axis": "Jungle",
                "value": 19.36
            },
            {
                "axis": "Top",
                "value": 20.41
            }
        ]
    },
    {
        "className": "H2K",
        "axes": [
            {
                "axis": "Mid",
                "value": 21.99
            },
            {
                "axis": "ADC",
                "value": 22.58
            },
            {
                "axis": "Support",
                "value": 14.83
            },
            {
                "axis": "Jungle",
                "value": 19.63
            },
            {
                "axis": "Top",
                "value": 20.96
            }
        ]
    },
    {
        "className": "S04",
        "axes": [
            {
                "axis": "Mid",
                "value": 23.18
            },
            {
                "axis": "ADC",
                "value": 22.55
            },
            {
                "axis": "Support",
                "value": 14.71
            },
            {
                "axis": "Jungle",
                "value": 18.99
            },
            {
                "axis": "Top",
                "value": 20.58
            }
        ]
    },
    {
        "className": "VIT",
        "axes": [
            {
                "axis": "Mid",
                "value": 21.57
            },
            {
                "axis": "ADC",
                "value": 22.78
            },
            {
                "axis": "Support",
                "value": 14.96
            },
            {
                "axis": "Jungle",
                "value": 19.36
            },
            {
                "axis": "Top",
                "value": 21.33
            }
        ]
    },
    {
        "className": "GIA",
        "axes": [
            {
                "axis": "Mid",
                "value": 22.27
            },
            {
                "axis": "ADC",
                "value": 22.1
            },
            {
                "axis": "Support",
                "value": 14.82
            },
            {
                "axis": "Jungle",
                "value": 19.11
            },
            {
                "axis": "Top",
                "value": 21.71
            }
        ]
    },
    {
        "className": "ROC",
        "axes": [
            {
                "axis": "Mid",
                "value": 22.61
            },
            {
                "axis": "ADC",
                "value": 23.97
            },
            {
                "axis": "Support",
                "value": 14.74
            },
            {
                "axis": "Jungle",
                "value": 18.53
            },
            {
                "axis": "Top",
                "value": 20.15
            }
        ]
    },
    {
        "className": "UOL",
        "axes": [
            {
                "axis": "Mid",
                "value": 22.29
            },
            {
                "axis": "ADC",
                "value": 22.89
            },
            {
                "axis": "Support",
                "value": 14.49
            },
            {
                "axis": "Jungle",
                "value": 18.86
            },
            {
                "axis": "Top",
                "value": 21.47
            }
        ]
    },
    {
        "className": "SPY",
        "axes": [
            {
                "axis": "Mid",
                "value": 21.77
            },
            {
                "axis": "ADC",
                "value": 23.65
            },
            {
                "axis": "Support",
                "value": 14.64
            },
            {
                "axis": "Jungle",
                "value": 18.82
            },
            {
                "axis": "Top",
                "value": 21.12
            }
        ]
    }
]